{
  "news": [
    {
      "text": "Disponibile la funzionalità di consultazione schede. In alto a sinistra, pulsante <i>Schede</i>.",
      "highlight": true,
      "order": 0
    },
    {
      "text": "Per assistenza scrivere a <a href='mailto:assistenza.atb@vigilfuoco.it'>assistenza.atb@vigilfuoco.it</a>.",
      "highlight": false,
      "order": 1
    },
    {
      "text": "Sono ora disponibili le qualifiche di <i>Allievo Vigile del Fuoco</i> e del personale volontario. Sono ora disponibili le qualifiche di <i>Allievo Vigile del Fuoco</i> e del personale volontario.",
      "highlight": false,
      "order": 2
    },
    {
      "text": "Lo sapevi che puoi aggiornare la situazione di un soggetto in una scheda ricercandola per <i>Numero Caso</i> e modificandone i campi?",
      "highlight": false,
      "order": 3
    }
  ]
}
